Workbook

Sheet ConversionTable
A1: Team Member | B1: New Key
A2: {=_xlfn.UNIQUE('All Colleagues'!D2:'All Colleagues'!D101)} -> Kevin Borich | B2: ="C" & TEXT(ROW()-1+100, "000") -> C101
A3: Les Claypool | B3: ="C" & TEXT(ROW()-1+100, "000") -> C102
A4: Chad Smith | B4: ="C" & TEXT(ROW()-1+100, "000") -> C103
A5: John Otto | B5: ="C" & TEXT(ROW()-1+100, "000") -> C104

Sheet All Colleagues
A1: Date | B1: Work | C1: Client | D1: Team Member | E1: Obfuscated | F1: Role | G1: Task Type | H1: Notes | I1: Time (Minutes) | J1: Fee Type | K1: ClientID | L1: WorkID
A2: 46083 | B2: BAS | C2: Bondi Bakery | D2: Kevin Borich | E2: =_xlfn.XLOOKUP(D2,ConversionTable!A$2:A$5, ConversionTable!B$2:B$5, "") -> C101 | F2: Bookkeeper | G2: Business Advisory | H2: prepare and review BAS workpapers | I2: 30 | J2: Time and Materials | L2: DIq2AnHTmt9O
A3: 46083 | B3: Bookkeeping | C3: Outback Logistics | D3: Kevin Borich | E3: =_xlfn.XLOOKUP(D3,ConversionTable!A$2:A$5, ConversionTable!B$2:B$5, "") -> C101 | F3: Bookkeeper | G3: Data Entry | H3: reconcile bank accounts for the month | I3: 60 | J3: Fixed Fee | L3: uFrEHS2JpDzf
A4: 46083 | B4: Compliance Review | C4: Mayfield Mechanical | D4: Les Claypool | E4: =_xlfn.XLOOKUP(D4,ConversionTable!A$2:A$5, ConversionTable!B$2:B$5, "") -> C102 | F4: Accountant | G4: Compliance | H4: review trust deed and minutes | I4: 30 | J4: Fixed Fee | L4: jc9LVC2JSxyj
A5: 46084 | B5: BAS | C5: Bluegum Constructions | D5: Chad Smith | E5: =_xlfn.XLOOKUP(D5,ConversionTable!A$2:A$5, ConversionTable!B$2:B$5, "") -> C103 | F5: Bookkeeper | G5: Business Advisory | H5: lodge BAS via portal | I5: 15 | J5: Fixed Fee | L5: WzPTpjRxcDm4
A6: 46086 | B6: BAS | C6: Claude 101 | D6: Kevin Borich | E6: =_xlfn.XLOOKUP(D6,ConversionTable!A$2:A$5, ConversionTable!B$2:B$5, "") -> C101 | F6: Bookkeeper | G6: BAS Preparation | H6: follow up missing supplier invoices for BAS | I6: 75 | J6: Fixed Fee | L6: SRABr1VjArnV
A7: 46087 | B7: Year End | C7: Saltwater Cafe | D7: Chad Smith | E7: =_xlfn.XLOOKUP(D7,ConversionTable!A$2:A$5, ConversionTable!B$2:B$5, "") -> C103 | F7: Bookkeeper | G7: Review | H7: reconcile balance sheet at year end | I7: 45 | J7: Fixed Fee | L7: RTWPElndTdtd
A8: 46087 | B8: Tax Planning | C8: Hunter Valley Wines Pty Ltd | D8: John Otto | E8: =_xlfn.XLOOKUP(D8,ConversionTable!A$2:A$5, ConversionTable!B$2:B$5, "") -> C104 | F8: Accountant | G8: Tax Planning | H8: review estimated tax position | I8: 25 | J8: Time and Materials | L8: QHqNgAC72qFl
A9: 46087 | B9: BAS | C9: Newcastle Surf Co | D9: Les Claypool | E9: =_xlfn.XLOOKUP(D9,ConversionTable!A$2:A$5, ConversionTable!B$2:B$5, "") -> C102 | F9: Accountant | G9: Business Advisory | H9: prepare and review BAS workpapers | I9: 50 | J9: Fixed Fee | L9: U1jjQKxKDpI6
A10: 46090 | B10: Payroll | C10: Mayfield Mechanical | D10: Chad Smith | E10: =_xlfn.XLOOKUP(D10,ConversionTable!A$2:A$5, ConversionTable!B$2:B$5, "") -> C103 | F10: Bookkeeper | G10: Compliance | H10: lodge SuperStream payment | I10: 30 | J10: Time and Materials | L10: X7TOrPMf7otY
A11: 46090 | B11: BAS | C11: Bondi Bakery | D11: Chad Smith | E11: =_xlfn.XLOOKUP(D11,ConversionTable!A$2:A$5, ConversionTable!B$2:B$5, "") -> C103 | F11: Bookkeeper | G11: BAS Preparation | H11: check fuel tax credits calculation | I11: 45 | J11: Fixed Fee | L11: DIq2AnHTmt9O
A12: 46090 | B12: BAS | C12: Newcastle Surf Co | D12: John Otto | E12: =_xlfn.XLOOKUP(D12,ConversionTable!A$2:A$5, ConversionTable!B$2:B$5, "") -> C104 | F12: Accountant | G12: Business Advisory | H12: lodge BAS via portal | I12: 240 | J12: Fixed Fee | L12: U1jjQKxKDpI6
A13: 46090 | B13: BAS | C13: Claude 101 | D13: Kevin Borich | E13: =_xlfn.XLOOKUP(D13,ConversionTable!A$2:A$5, ConversionTable!B$2:B$5, "") -> C101 | F13: Bookkeeper | G13: Compliance | H13: prepare and review BAS workpapers | I13: 75 | J13: Fixed Fee | L13: gxwvqcCh5esM
... A101: 46136 | B101: Tax Planning | C101: Wallsend Hardware | D101: Les Claypool | E101: =_xlfn.XLOOKUP(D101,ConversionTable!A$2:A$5, ConversionTable!B$2:B$5, "") -> C102 | F101: Accountant | G101: Business Advisory | H101: prepare year-end tax plan draft | I101: 150 | J101: Time and Materials | L101: pfbH9vOWOU6m

Sheet John Otto
A1: Date | B1: Work | C1: Client | D1: Role | E1: Task Type | F1: Notes | G1: Time (Minutes) | H1: Fee Type | I1: ClientID | J1: WorkID
A2: 46087 | B2: Tax Planning | C2: Hunter Valley Wines Pty Ltd | D2: Accountant | E2: Tax Planning | F2: review estimated tax position | G2: 25 | H2: Time and Materials | J2: QHqNgAC72qFl
A3: 46090 | B3: BAS | C3: Newcastle Surf Co | D3: Accountant | E3: Business Advisory | F3: lodge BAS via portal | G3: 240 | H3: Fixed Fee | J3: U1jjQKxKDpI6
A4: 46092 | B4: Superannuation | C4: Betty's Cakes | D4: Accountant | E4: SMSF | F4: review contributions cap position | G4: 210 | H4: Fixed Fee | J4: mq6OLkTkx9NI
A5: 46097 | B5: Tax Return | C5: Outback Logistics | D5: Accountant | E5: Tax Return | F5: prepare draft tax return | G5: 105 | H5: Fixed Fee | J5: 3BpdbIKaRdeb
A6: 46099 | B6: Year End | C6: Outback Logistics | D6: Accountant | E6: Review | F6: reconcile loan accounts | G6: 45 | H6: Fixed Fee | J6: Ovz1dOOdTXgl
A7: 46099 | B7: Onboarding | C7: ACME 123 | D7: Accountant | E7: Bookkeeping | F7: set up Xero file for new client | G7: 60 | H7: Fixed Fee | J7: brnTP3fAbnFb
A8: 46100 | B8: Compliance Review | C8: Saltwater Cafe | D8: Accountant | E8: Compliance | F8: review prior period workpapers | G8: 75 | H8: Fixed Fee | J8: RTWPElndTdtd
A9: 46106 | B9: Year End | C9: Wallsend Hardware | D9: Accountant | E9: Review | F9: year end adjustment journals | G9: 60 | H9: Fixed Fee | J9: Y7gbtP7ySeQM
A10: 46106 | B10: Superannuation | C10: Merewether Yoga Studio | D10: Accountant | E10: Superannuation | F10: prepare SMSF financial statements | G10: 60 | H10: Time and Materials | J10: KPfA1lquCu2r
A11: 46107 | B11: Superannuation | C11: Saltwater Cafe | D11: Accountant | E11: Superannuation | F11: review contributions cap position | G11: 90 | H11: Fixed Fee | J11: ilC2eY1gOHaf
A12: 46111 | B12: Superannuation | C12: Bluegum Constructions | D12: Accountant | E12: Superannuation | F12: document investment strategy review | G12: 60 | H12: Fixed Fee | J12: WzPTpjRxcDm4
A13: 46111 | B13: Tax Planning | C13: Harbour View Real Estate | D13: Accountant | E13: Business Advisory | F13: model trust distribution scenarios | G13: 75 | H13: Time and Materials | J13: xJpRa5HSUPwe
... A27: 46135 | B27: Superannuation | C27: Cessnock Earthmoving | D27: Accountant | E27: Superannuation | F27: reconcile SMSF bank feed | G27: 105 | H27: Fixed Fee | J27: RsQXXJcHPeOa

Sheet Chad Smith
A1: Date | B1: Work | C1: Client | D1: Role | E1: Task Type | F1: Notes | G1: Time (Minutes) | H1: Fee Type | I1: ClientID | J1: WorkID
A2: 46084 | B2: BAS | C2: Bluegum Constructions | D2: Bookkeeper | E2: Business Advisory | F2: lodge BAS via portal | G2: 15 | H2: Fixed Fee | J2: WzPTpjRxcDm4
A3: 46087 | B3: Year End | C3: Saltwater Cafe | D3: Bookkeeper | E3: Review | F3: reconcile balance sheet at year end | G3: 45 | H3: Fixed Fee | J3: RTWPElndTdtd
A4: 46090 | B4: Payroll | C4: Mayfield Mechanical | D4: Bookkeeper | E4: Compliance | F4: lodge SuperStream payment | G4: 30 | H4: Time and Materials | J4: X7TOrPMf7otY
A5: 46090 | B5: BAS | C5: Bondi Bakery | D5: Bookkeeper | E5: BAS Preparation | F5: check fuel tax credits calculation | G5: 45 | H5: Fixed Fee | J5: DIq2AnHTmt9O
A6: 46093 | B6: Bookkeeping | C6: Eagles Nest Holdings | D6: Bookkeeper | E6: Reconciliation | F6: review uncoded statement lines | G6: 75 | H6: Time and Materials | J6: V6b2JD6sy3ZH
A7: 46094 | B7: Year End | C7: Burger Town | D7: Bookkeeper | E7: Year End | F7: reconcile loan accounts | G7: 45 | H7: Fixed Fee | J7: 4CqpIqK3yn9F
A8: 46099 | B8: Payroll | C8: Maitland Motors | D8: Bookkeeper | E8: STP | F8: STP finalisation review | G8: 20 | H8: Fixed Fee | J8: tUeC99enq522
A9: 46101 | B9: Payroll | C9: Coastal Plumbing Services | D9: Bookkeeper | E9: Compliance | F9: lodge SuperStream payment | G9: 120 | H9: Fixed Fee | J9: 1sNLjVHWGaub
A10: 46104 | B10: Payroll | C10: Charlestown Dental | D10: Bookkeeper | E10: STP | F10: STP finalisation review | G10: 60 | H10: Fixed Fee | J10: q3UjrnvQ0Fp4
A11: 46114 | B11: BAS | C11: Saltwater Cafe | D11: Bookkeeper | E11: BAS Preparation | F11: follow up missing supplier invoices for BAS | G11: 90 | H11: Fixed Fee | J11: UozD13kay5Wr
A12: 46115 | B12: Payroll | C12: Singleton Smash Repairs | D12: Bookkeeper | E12: Compliance | F12: process termination pay | G12: 45 | H12: Fixed Fee | J12: DBTq0Zf2pCLx
A13: 46115 | B13: Bookkeeping | C13: Hunter Valley Wines Pty Ltd | D13: Bookkeeper | E13: Bookkeeping | F13: fix coding errors from prior month | G13: 75 | H13: Fixed Fee | J13: QHqNgAC72qFl
... A26: 46136 | B26: Bookkeeping | C26: Betty's Cakes | D26: Bookkeeper | E26: Data Entry | F26: process supplier invoices | G26: 90 | H26: Fixed Fee | J26: mq6OLkTkx9NI

Sheet Les Claypool
A1: Date | B1: Work | C1: Client | D1: Role | E1: Task Type | F1: Notes | G1: Time (Minutes) | H1: Fee Type | I1: ClientID | J1: WorkID
A2: 46083 | B2: Compliance Review | C2: Mayfield Mechanical | D2: Accountant | E2: Compliance | F2: review trust deed and minutes | G2: 30 | H2: Fixed Fee | J2: jc9LVC2JSxyj
A3: 46087 | B3: BAS | C3: Newcastle Surf Co | D3: Accountant | E3: Business Advisory | F3: prepare and review BAS workpapers | G3: 50 | H3: Fixed Fee | J3: U1jjQKxKDpI6
A4: 46090 | B4: Tax Return | C4: Wallsend Hardware | D4: Accountant | E4: Tax Return | F4: prepare draft tax return | G4: 15 | H4: Fixed Fee | J4: bjhPInRVkLUh
A5: 46091 | B5: BAS | C5: Claude 101 | D5: Accountant | E5: Compliance | F5: prepare and review BAS workpapers | G5: 30 | H5: Fixed Fee | J5: gxwvqcCh5esM
A6: 46092 | B6: Business Advisory | C6: Newcastle Surf Co | D6: Accountant | E6: Strategic Planning | F6: budget vs actual variance analysis | G6: 45 | H6: Time and Materials | J6: U1jjQKxKDpI6
A7: 46101 | B7: Business Advisory | C7: Burger Town | D7: Accountant | E7: Business Advisory | F7: review monthly management reports | G7: 120 | H7: Time and Materials | J7: 4CqpIqK3yn9F
A8: 46101 | B8: Year End | C8: Betty's Cakes | D8: Accountant | E8: Review | F8: reconcile balance sheet at year end | G8: 40 | H8: Fixed Fee | J8: JRcoreogrNww
A9: 46101 | B9: Onboarding | C9: Lake Mac Landscaping | D9: Accountant | E9: Bookkeeping | F9: set up bank feeds | G9: 180 | H9: Fixed Fee | J9: XP9K63LSFZH3
A10: 46105 | B10: BAS | C10: Outback Logistics | D10: Accountant | E10: BAS Preparation | F10: follow up missing supplier invoices for BAS | G10: 105 | H10: Fixed Fee | J10: 3BpdbIKaRdeb
A11: 46108 | B11: Year End | C11: Merewether Yoga Studio | D11: Accountant | E11: Review | F11: review trial balance | G11: 75 | H11: Fixed Fee | J11: EqEyPXS058H4
A12: 46111 | B12: Tax Planning | C12: Harbour View Real Estate | D12: Accountant | E12: Tax Planning | F12: prepare year-end tax plan draft | G12: 60 | H12: Fixed Fee | J12: xJpRa5HSUPwe
A13: 46112 | B13: Superannuation | C13: Betty's Cakes | D13: Accountant | E13: Superannuation | F13: reconcile SMSF bank feed | G13: 30 | H13: Fixed Fee | J13: JRcoreogrNww
... A25: 46136 | B25: Tax Planning | C25: Wallsend Hardware | D25: Accountant | E25: Business Advisory | F25: prepare year-end tax plan draft | G25: 150 | H25: Time and Materials | J25: pfbH9vOWOU6m

Sheet Kevin Borich
A1: Date | B1: Work | C1: Client | D1: Role | E1: Task Type | F1: Notes | G1: Time (Minutes) | H1: Fee Type | I1: ClientID | J1: WorkID
A2: 46083 | B2: BAS | C2: Bondi Bakery | D2: Bookkeeper | E2: Business Advisory | F2: prepare and review BAS workpapers | G2: 30 | H2: Time and Materials | J2: DIq2AnHTmt9O
A3: 46083 | B3: Bookkeeping | C3: Outback Logistics | D3: Bookkeeper | E3: Data Entry | F3: reconcile bank accounts for the month | G3: 60 | H3: Fixed Fee | J3: uFrEHS2JpDzf
A4: 46086 | B4: BAS | C4: Claude 101 | D4: Bookkeeper | E4: BAS Preparation | F4: follow up missing supplier invoices for BAS | G4: 75 | H4: Fixed Fee | J4: SRABr1VjArnV
A5: 46090 | B5: BAS | C5: Claude 101 | D5: Bookkeeper | E5: Compliance | F5: prepare and review BAS workpapers | G5: 75 | H5: Fixed Fee | J5: gxwvqcCh5esM
A6: 46091 | B6: Bookkeeping | C6: Wallsend Hardware | D6: Bookkeeper | E6: Bookkeeping | F6: review uncoded statement lines | G6: 40 | H6: Fixed Fee | J6: bjhPInRVkLUh
A7: 46091 | B7: Year End | C7: Cessnock Earthmoving | D7: Bookkeeper | E7: Year End | F7: review trial balance | G7: 30 | H7: Fixed Fee | J7: RsQXXJcHPeOa
A8: 46094 | B8: Payroll | C8: Maitland Motors | D8: Bookkeeper | E8: Payroll | F8: STP finalisation review | G8: 60 | H8: Fixed Fee | J8: KMzKG5mSoyPs
A9: 46099 | B9: Bookkeeping | C9: Bondi Bakery | D9: Bookkeeper | E9: Bookkeeping | F9: process supplier invoices | G9: 25 | H9: Fixed Fee | J9: 2Ztd26fEeVVh
A10: 46099 | B10: Year End | C10: Lake Mac Landscaping | D10: Bookkeeper | E10: Compliance | F10: roll forward client file | G10: 35 | H10: Fixed Fee | J10: XP9K63LSFZH3
A11: 46100 | B11: Year End | C11: Harbour View Real Estate | D11: Bookkeeper | E11: Compliance | F11: prepare financial statements | G11: 90 | H11: Fixed Fee | J11: xJpRa5HSUPwe
A12: 46101 | B12: Onboarding | C12: Betty's Cakes | D12: Bookkeeper | E12: Bookkeeping | F12: configure chart of accounts | G12: 40 | H12: Fixed Fee | J12: mq6OLkTkx9NI
A13: 46106 | B13: Onboarding | C13: Wallsend Hardware | D13: Bookkeeper | E13: Setup | F13: set up bank feeds | G13: 10 | H13: Fixed Fee | J13: Y7gbtP7ySeQM
... A26: 46134 | B26: BAS | C26: Hunter Valley Wines Pty Ltd | D26: Bookkeeper | E26: Compliance | F26: follow up missing supplier invoices for BAS | G26: 45 | H26: Time and Materials | J26: QHqNgAC72qFl
